niveristand/__init__.py
niveristand/_auto_generated_classes.py
niveristand/_decorators.py
niveristand/_errormessages.py
niveristand/_internal.py
niveristand/errors.py
niveristand/realtimesequencetools.py
niveristand/_translation/__init__.py
niveristand/_translation/custom_action_symbols.py
niveristand/_translation/symbols.py
niveristand/_translation/utils.py
niveristand/_translation/py2rtseq/__init__.py
niveristand/_translation/py2rtseq/assign_transformer.py
niveristand/_translation/py2rtseq/attribute_transformer.py
niveristand/_translation/py2rtseq/augassign_transformer.py
niveristand/_translation/py2rtseq/binaryoperator_transformer.py
niveristand/_translation/py2rtseq/booloperator_transformer.py
niveristand/_translation/py2rtseq/break_transformer.py
niveristand/_translation/py2rtseq/call_transformer.py
niveristand/_translation/py2rtseq/compareoperator_transformer.py
niveristand/_translation/py2rtseq/constant_transformer.py
niveristand/_translation/py2rtseq/custom_generate_error.py
niveristand/_translation/py2rtseq/custom_localhost_wait.py
niveristand/_translation/py2rtseq/custom_math_log.py
niveristand/_translation/py2rtseq/custom_nivs_yield.py
niveristand/_translation/py2rtseq/custom_stop_task.py
niveristand/_translation/py2rtseq/default_transformer.py
niveristand/_translation/py2rtseq/exp_transformer.py
niveristand/_translation/py2rtseq/for_transformer.py
niveristand/_translation/py2rtseq/functiondef_transformer.py
niveristand/_translation/py2rtseq/if_transformer.py
niveristand/_translation/py2rtseq/ifexp_transformer.py
niveristand/_translation/py2rtseq/index_transformer.py
niveristand/_translation/py2rtseq/list_transformer.py
niveristand/_translation/py2rtseq/module_transformer.py
niveristand/_translation/py2rtseq/name_transformer.py
niveristand/_translation/py2rtseq/nameconstant_transformer.py
niveristand/_translation/py2rtseq/num_transformer.py
niveristand/_translation/py2rtseq/pass_transformer.py
niveristand/_translation/py2rtseq/return_transformer.py
niveristand-3.2.3.dist-info/LICENSE
niveristand-3.2.3.dist-info/METADATA
niveristand-3.2.3.dist-info/WHEEL
niveristand-3.2.3.dist-info/top_level.txt
niveristand-3.2.3.dist-info/RECORD
