Metadata-Version: 2.1
Name: niveristand
Version: 3.2.3
Summary: NI VeriStand Python API
Home-page: https://github.com/ni/niveristand-python
Author: National Instruments
Maintainer: Marcelo Izaguirre
Maintainer-email: marcelo.izaguirre@ni.com
License: MIT
Keywords: niveristand,veristand
Classifier: Development Status :: 5 - Production/Stable
Classifier: Intended Audience :: Developers
Classifier: Intended Audience :: Science/Research
Classifier: License :: OSI Approved :: MIT License
Classifier: Operating System :: Microsoft :: Windows
Classifier: Programming Language :: Python
Classifier: Programming Language :: Python :: Implementation :: CPython
Classifier: Programming Language :: Python :: Implementation :: PyPy
Classifier: Topic :: Software Development :: Testing
License-File: LICENSE
Requires-Dist: pythonnet~=3.0.1
Requires-Dist: PyYAML
